bin/__init__.py
bin/godbatch.py
bin/godfile.py
bin/godimage.py
bin/godjob.py
bin/godlogin.py
bin/godproject.py
bin/godssh.py
bin/goduser.py
godocker_CLI-1.0.25.dist-info/DESCRIPTION.rst
godocker_CLI-1.0.25.dist-info/METADATA
godocker_CLI-1.0.25.dist-info/RECORD
godocker_CLI-1.0.25.dist-info/WHEEL
godocker_CLI-1.0.25.dist-info/entry_points.txt
godocker_CLI-1.0.25.dist-info/metadata.json
godocker_CLI-1.0.25.dist-info/top_level.txt
godockercli/__init__.py
godockercli/auth.py
godockercli/httputils.py
godockercli/utils.py
