Metadata-Version: 2.0
Name: godocker-CLI
Version: 1.0.25
Summary: GO Docker CLI
Home-page: UNKNOWN
Author: Olivier Sallou
Author-email: olivier.sallou@irisa.fr
License: UNKNOWN
Platform: UNKNOWN
Requires-Dist: click
Requires-Dist: humanfriendly
Requires-Dist: nose
Requires-Dist: pyCLI (>=2.0.3)
Requires-Dist: requests (>=2.7.0)
Requires-Dist: terminaltables (>=1.0.2)
